_lamonpy.cp37-win_amd64.pyd
_lamonpy_avx.cp37-win_amd64.pyd
_lamonpy_avx2.cp37-win_amd64.pyd
lamonpy/__init__.py
lamonpy/dict.bin
lamonpy/tagger.bin
lamonpy-0.2.0.dist-info/LICENSE
lamonpy-0.2.0.dist-info/METADATA
lamonpy-0.2.0.dist-info/WHEEL
lamonpy-0.2.0.dist-info/top_level.txt
lamonpy-0.2.0.dist-info/RECORD
